setup.py
hadoop_manager.egg-info/PKG-INFO
hadoop_manager.egg-info/SOURCES.txt
hadoop_manager.egg-info/dependency_links.txt
hadoop_manager.egg-info/top_level.txt
hadoop_manager.egg-info/zip-safe
hdpmanager/__init__.py
hdpmanager/combiner.py
hdpmanager/counter.py
hdpmanager/hdpenv.py
hdpmanager/hdpfs.py
hdpmanager/hdpjob.py
hdpmanager/hdpmanager.py
hdpmanager/mapper.py
hdpmanager/protocol.py
hdpmanager/reducer.py
hdpmanager/streamer.py