Metadata-Version: 1.0
Name: hadoop-manager
Version: 0.0.1
Summary: Python wrapper for hadoop.
Home-page: https://github.com/Zemanta/hadoop-manager
Author: Jure Ham
Author-email: jure.ham@zemanta.com
License: GPLv3
Platform: any
